Metadata-Version: 2.1
Name: django-admin-related
Version: 0.2
Summary: The "Django Admin Related" prevents you from deleting your models if you have related items
Home-page: https://github.com/shinneider/django_admin_related
Author: Shinneider Libanio da Silva
Author-email: shinneider-libanio@hotmail.com
License: MIT
Platform: UNKNOWN
Requires-Python: >=3.3
